mwalib-1.8.7.dist-info/METADATA
mwalib-1.8.7.dist-info/WHEEL
mwalib-1.8.7.dist-info/licenses/LICENSE
mwalib-1.8.7.dist-info/licenses/LICENSE-cfitsio
mwalib/__init__.py
mwalib/__init__.pyi
mwalib/py.typed
mwalib/mwalib.cpython-39-darwin.so
mwalib-1.8.7.dist-info/RECORD
