Metadata-Version: 2.4
Name: mwalib
Version: 1.8.7
Classifier: Development Status :: 5 - Production/Stable
Classifier: Intended Audience :: Science/Research
Classifier: Topic :: Scientific/Engineering :: Astronomy
Classifier: License :: OSI Approved :: Mozilla Public License 2.0 (MPL 2.0)
Classifier: Programming Language :: Python :: 3.9
Classifier: Programming Language :: Python :: 3.10
Classifier: Programming Language :: Python :: 3.11
Classifier: Programming Language :: Python :: 3.12
Classifier: Programming Language :: Python :: 3.13
Classifier: Programming Language :: Python :: 3 :: Only
Requires-Dist: numpy
License-File: LICENSE
License-File: LICENSE-cfitsio
Summary: A library to work with raw data and metadata from the Murchison Widefield Array (MWA)
Keywords: MWA,radioastronomy
Home-Page: https://github.com/MWATelescope/mwalib
Author: Greg Sleap <greg.sleap@curtin.edu.au>, Christopher H. Jordan <christopherjordan87@gmail.com>
Author-email: Greg Sleap <greg.sleap@curtin.edu.au>, "Christopher H. Jordan" <christopherjordan87@gmail.com>, Dev Null <dev.null@curtin.edu.au>
Maintainer-email: Greg Sleap <greg.sleap@curtin.edu.au>
License: MPL-2.0
Requires-Python: >=3.9
Project-URL: Homepage, https://github.com/MWATelescope/mwalib
Project-URL: Bug Reports, https://github.com/MWATelescope/mwalib/issues
Project-URL: Source, https://github.com/MWATelescope/mwalib
